qlib/__init__.py
qlib/qadapter.py
qlib/qfacade.py
qlib/qlibbase.py
qlib/manual_decline/__init__.py
qlib/manual_decline/arps.py
qlib/manual_decline/arpsfcn.py
qlib/manual_decline/fitarps.py
qlib/manual_decline/fitthb.py
qlib/manual_decline/testing.py
qlib/manual_decline/thb2arps.py
qlib/manual_decline/thbfcn.py
tests/__init__.py
tests/test_qapi.py
qlib-0.0.2.dev20.dist-info/LICENSE
qlib-0.0.2.dev20.dist-info/METADATA
qlib-0.0.2.dev20.dist-info/WHEEL
qlib-0.0.2.dev20.dist-info/top_level.txt
qlib-0.0.2.dev20.dist-info/RECORD
